bles/__init__.py
bles/py.typed
bles-0.3.1.dist-info/LICENSE.md
bles-0.3.1.dist-info/METADATA
bles-0.3.1.dist-info/WHEEL
bles-0.3.1.dist-info/RECORD
